README.rst
setup.py
celery_sqlalchemy_scheduler/__init__.py
celery_sqlalchemy_scheduler/models.py
celery_sqlalchemy_scheduler/schedulers.py
celery_sqlalchemy_scheduler/session.py
celery_sqlalchemy_scheduler/tzcrontab.py
celery_sqlalchemy_scheduler_hotstar.egg-info/PKG-INFO
celery_sqlalchemy_scheduler_hotstar.egg-info/SOURCES.txt
celery_sqlalchemy_scheduler_hotstar.egg-info/dependency_links.txt
celery_sqlalchemy_scheduler_hotstar.egg-info/not-zip-safe
celery_sqlalchemy_scheduler_hotstar.egg-info/requires.txt
celery_sqlalchemy_scheduler_hotstar.egg-info/top_level.txt