Metadata-Version: 1.1
Name: celery-sqlalchemy-scheduler-hotstar
Version: 0.2.4
Summary: A Scheduler Based SQLalchemy For Celery
Home-page: https://github.com/gsingh42/celery-sqlalchemy-scheduler
Author: Gaurav Singh
Author-email: guarav.s@hotstar.com
License: MIT
Keywords: celery scheduler sqlalchemy beat
Platform: any
Classifier: Development Status :: 3 - Alpha
Classifier: Intended Audience :: Developers
Classifier: Topic :: Software Development :: Libraries
Classifier: License :: OSI Approved :: MIT License
Classifier: Programming Language :: Python :: 3
Classifier: Programming Language :: Python :: 3.6
